{
  "enable": {
    "READ": false,
    "STATS": false,
    "SPLIT": true,
    "EXTRACT_ACC_LIST": false 
  },
  "defaults": {
    "input_file": "sol_101_airbus.exp",
    "input_dir": "../perf_test"
  },
  "actions": {
    "READ": {
      "output_file": "result.txt"
    },
    "STATS": {},
    "SPLIT": {
      "output_dir": "result_dir"
    },
    "EXTRACT_ACC_LIST": {
      "output_file": "result.txt",
      "output_dir": "result_dir",
      "option_01": "GRID",
      "input_01": "extract_ids.txt"
    }
  }
}
